MANIFEST.in
README.rst
setup.cfg
setup.py
bin/pfstorage
pfstorage/__init__.py
pfstorage/pfstorage.py
pfstorage.egg-info/PKG-INFO
pfstorage.egg-info/SOURCES.txt
pfstorage.egg-info/dependency_links.txt
pfstorage.egg-info/not-zip-safe
pfstorage.egg-info/requires.txt
pfstorage.egg-info/top_level.txt