Metadata-Version: 1.0
Name: pfstorage
Version: 2.0.0.0
Summary: object storage interface
Home-page: https://github.com/FNNDSC/pfstorage
Author: Rudolph Pienaar
Author-email: rudolph.pienaar@gmail.com
License: MIT
Platform: UNKNOWN
